spatplotlib/__init__.py
spatplotlib/display.py
spatplotlib/exporter.py
spatplotlib/htmlbase.py
spatplotlib/htmlipynb.py
spatplotlib/leaflet_renderer.py
spatplotlib/links.py
spatplotlib/maptiles.py
spatplotlib/renderer.py
spatplotlib/utils.py
spatplotlib-1.0.0.dist-info/AUTHORS.md
spatplotlib-1.0.0.dist-info/LICENSE
spatplotlib-1.0.0.dist-info/METADATA
spatplotlib-1.0.0.dist-info/WHEEL
spatplotlib-1.0.0.dist-info/top_level.txt
spatplotlib-1.0.0.dist-info/RECORD
