Metadata-Version: 2.1
Name: spatplotlib
Version: 1.0.0
Summary: Spatial plotting with Leaflet and Matplotlib. Forked from parts of both mplleaflet and mplexporter.
Home-page: https://github.com/ralian/spatplotlib
Author: Will Bowers
Author-email: wbowers314@gmail.com
License: BSD 3-clause
License-File: LICENSE
License-File: AUTHORS.md
